git_commit_mcp/__init__.py
git_commit_mcp/__main__.py
git_commit_mcp/ai_client.py
git_commit_mcp/change_tracker.py
git_commit_mcp/changelog_manager.py
git_commit_mcp/config.py
git_commit_mcp/git_operations.py
git_commit_mcp/logging_config.py
git_commit_mcp/message_generator.py
git_commit_mcp/models.py
git_commit_mcp/repository_manager.py
git_commit_mcp/server.py
git_commit_mcp_server-0.1.3.dist-info/METADATA
git_commit_mcp_server-0.1.3.dist-info/WHEEL
git_commit_mcp_server-0.1.3.dist-info/entry_points.txt
git_commit_mcp_server-0.1.3.dist-info/licenses/LICENSE
git_commit_mcp_server-0.1.3.dist-info/RECORD
