Metadata-Version: 2.4
Name: git-commit-mcp-server
Version: 0.1.3
Summary: MCP server for automated Git commit workflows with conventional commit messages
Project-URL: Homepage, https://github.com/surajfale/git-mcp-server
Project-URL: Repository, https://github.com/surajfale/git-mcp-server
Project-URL: Issues, https://github.com/surajfale/git-mcp-server/issues
Project-URL: Documentation, https://github.com/surajfale/git-mcp-server#readme
Author-email: Suraj Fale <surajfale1@gmail.com>
License: MIT
License-File: LICENSE
Keywords: automation,changelog,commit,conventional-commits,git,mcp
Classifier: Development Status :: 4 - Beta
Classifier: Intended Audience :: Developers
Classifier: License :: OSI Approved :: MIT License
Classifier: Programming Language :: Python :: 3
Classifier: Programming Language :: Python :: 3.10
Classifier: Programming Language :: Python :: 3.11
Classifier: Programming Language :: Python :: 3.12
Classifier: Topic :: Software Development :: Libraries :: Python Modules
Classifier: Topic :: Software Development :: Version Control :: Git
Requires-Python: >=3.10
Requires-Dist: fastmcp>=0.1.0
Requires-Dist: gitpython>=3.1.0
Requires-Dist: openai>=1.50.0
Requires-Dist: python-dotenv>=1.0.0
Provides-Extra: dev
Requires-Dist: pytest-asyncio>=0.21.0; extra == 'dev'
Requires-Dist: pytest-cov>=4.1.0; extra == 'dev'
Requires-Dist: pytest>=7.4.0; extra == 'dev'
